shrs/AdditionalAnalysis.py
shrs/DesignIdentifyPrimer.py
shrs/DesignProbe.py
shrs/DesignUniversalPrimer.py
shrs/InputSequencePreprocessing.py
shrs/__init__.py
shrs/__main__.py
shrs/insilicoPCR.py
shrs-0.13.2.dist-info/licenses/LICENSE
shrslib/__init__.py
shrslib/__version__.py
shrslib/basicfunc.py
shrslib/explore.py
shrslib/multiprocessfunc.py
shrslib/scores.py
shrs-0.13.2.dist-info/METADATA
shrs-0.13.2.dist-info/WHEEL
shrs-0.13.2.dist-info/entry_points.txt
shrs-0.13.2.dist-info/top_level.txt
shrs-0.13.2.dist-info/RECORD
