Metadata-Version: 2.4
Name: shrs
Version: 0.13.2
Summary: This package contains the programs that design primer set for microbiological analysis and perform some accessory analysis.
Author: Masayuki TAKAHASHI
Author-email: mdottakahashi@gmail.com
License: MIT License
Classifier: Development Status :: 4 - Beta
Classifier: Intended Audience :: Science/Research
Classifier: Programming Language :: Python :: 3
Classifier: Programming Language :: Python :: 3.8
Classifier: License :: OSI Approved :: MIT License
Classifier: Operating System :: OS Independent
Classifier: Topic :: Scientific/Engineering :: Bio-Informatics
Requires-Python: >=3.8
License-File: LICENSE
Requires-Dist: psutil
Requires-Dist: numpy
Requires-Dist: pandas
Requires-Dist: scipy
Requires-Dist: tqdm
Requires-Dist: chardet
Requires-Dist: biopython
Requires-Dist: matplotlib
Requires-Dist: dendropy
Provides-Extra: gpu
Requires-Dist: cupy; extra == "gpu"
Dynamic: license-file
